{
  "nextId": 2,
  "tasks": [
    {
      "id": "1",
      "subject": "Audit test coverage for slash command interceptor refactor and feedback handling",
      "description": "Identify missing test coverage for feedback events in TUI, HTTP conduit, and session stream; edge cases for slash command parsing; provide recommendations for new tests and refactoring if needed.",
      "status": "pending",
      "activeForm": "Auditing test coverage",
      "metadata": {},
      "blocks": [],
      "blockedBy": [],
      "createdAt": 1780842368271,
      "updatedAt": 1780842368271
    }
  ]
}